fulladder.v
/*
Full Adder model in Verilog w/ testbench.
Compile with: iverilog -wimplicit -c filelist.txt -o fulladder.vvp 
*/
module full_adder(A, B, Cin, Sum, Cout);

input A, B, Cin;
output Sum, Cout;
wire w1, w2, w3; //wires needed other than inputs/outputs

// create gates
xor sumXOR(Sum, A, B, Cin); //(output, inputs)
and AND1(w1, A, B);
and AND2(w2, A, Cin);
and AND3(w3, B, Cin);
or coutOR(Cout, w1, w2, w3);


endmodule

fulladder_tb.v
module full_adder_tb;

reg A, B, Cin; //input regs
wire Sum, Cout; //Output wires

wire[1:0] result;
assign result = A + B + Cin; //result[1] == Cout, result[0] = Sum

//Instantiate module to test
full_adder adder(
    .A(A), 
    .B(B),
    .Cin(Cin),
    .Sum(Sum),
    .Cout(Cout));

//Init reg inputs
initial begin
    $dumpfile("fulladder_wvfrm.vcd");
    $dumpvars(0, full_adder_tb);
    A = 0;
    B = 0;
    Cin = 0;
    #80 //delay 80ns
    $finish;
end

 //Manipulate inputs (toggle @ different intervals indefinitely)
always begin
     #10 A =~ A;
end

always begin
    #20 B =~ B;
end

always begin
    #40 Cin =~ Cin;
end

//Display results whenever A, B, Cin change
always @(A, B, Cin) begin
    #1; //Small delay for lines to stabilize
    if ((Sum == result[0]) && (Cout == result[1])) begin // Compare outputs to expected results
        $display("PASSED - A: %b, B: %b, Cin: %b, Sum: %b, Cout: %b", A, B, Cin, Sum, Cout);
    end else begin
        $display("FAILED - A: %b, B: %b, Cin: %b, Sum: %b, Cout: %b => EXPECTED - Sum: %b, Cout: %b", A, B, Cin, Sum, Cout, result[0], result[1]);
    end
    
end

endmodule

fulladder_wvfrm.vcd
$date
	Wed Jan 18 15:40:52 2023
$end
$version
	Icarus Verilog
$end
$timescale
	1s
$end
$scope module full_adder_tb $end
$var wire 2 ! result [1:0] $end
$var wire 1 " Sum $end
$var wire 1 # Cout $end
$var reg 1 $ A $end
$var reg 1 % B $end
$var reg 1 & Cin $end
$scope module adder $end
$var wire 1 $ A $end
$var wire 1 % B $end
$var wire 1 & Cin $end
$var wire 1 # Cout $end
$var wire 1 " Sum $end
$var wire 1 ' w1 $end
$var wire 1 ( w2 $end
$var wire 1 ) w3 $end
$upscope $end
$upscope $end
$enddefinitions $end
#0
$dumpvars
0)
0(
0'
0&
0%
0$
0#
0"
b0 !
$end
#10
1"
b1 !
1$
#20
0$
b1 !
1%
#30
1#
0"
1'
b10 !
1$
#40
0#
0'
1"
0$
0%
b1 !
1&
#50
1#
0"
1(
b10 !
1$
#60
0(
1)
0$
b10 !
1%
#70
1"
1'
1(
b11 !
1$
#80
0#
0'
0"
0(
0)
0$
0%
b0 !
0&
