fulladder.v
/*
Full Adder model in Verilog w/ testbench.
Compile with: iverilog -wimplicit -c filelist.txt -o fulladder.vvp 
*/
module full_adder(A, B, Cin, Sum, Cout);

input A, B, Cin;
output Sum, Cout;
wire w1, w2, w3; //wires needed other than inputs/outputs

// create gates
xor sumXOR(Sum, A, B, Cin); //(output, inputs)
and AND1(w1, A, B);
and AND2(w2, A, Cin);
and AND3(w3, B, Cin);
or coutOR(Cout, w1, w2, w3);


endmodule

twobitadder.v
`include "fulladder.v"

module twobitadder(A, B, Cin, Sum, Cout);

input [1:0] A, B;
input Cin;

output [1:0] Sum;
output Cout;

wire w1;

full_adder add1(A[0], B[0], Cin, Sum[0], w1);
full_adder add2(A[1], B[1], w1, Sum[1], Cout);

endmodule

twobitadder_tb.v
//`include "twobitadder.v"

module twobitadder_tb;

wire [1:0] A, B;
wire Cin;

wire [1:0] Sum;
wire Cout; 

wire [2:0] result;
assign result = A + B + Cin;

twobitadder tba(A, B, Cin, Sum, Cout); //Instantiate module to test

integer i;
assign {Cin, A, B} = i[4:0]; //Cin = i[4], A = i[3:2], B = i[1:0]

initial begin
    $dumpfile("tba_wvfrm.vcd");
    $dumpvars(0, twobitadder_tb);
    for (i = 0; i < 32; i++) begin
        #20; //stabilize outputs for 20ns
        if ((Cout == result[2]) && (Sum == result[1:0])) begin
            $display("PASSED - A: %b, B: %b, Cin: %b --> Cout: %b, Sum: %b", A, B, Cin, Cout, Sum);
        end else begin
            $display("FAILED - A: %b, B: %b, Cin: %b --> Cout: %b, Sum: %b - EXPECTED: %b", A, B, Cin, Cout, Sum, result);
        end
    end
    $finish;
end

/*
for (A=2'b00; A<=2'b11; A=A+1) begin
    $display("%b", A[0]);
end*/


endmodule

tba_wvfrm.vcd
$date
	Wed Jan 18 16:38:35 2023
$end
$version
	Icarus Verilog
$end
$timescale
	1s
$end
$scope module twobitadder_tb $end
$var wire 3 ! result [2:0] $end
$var wire 2 " Sum [1:0] $end
$var wire 1 # Cout $end
$var wire 1 $ Cin $end
$var wire 2 % B [1:0] $end
$var wire 2 & A [1:0] $end
$var integer 32 ' i [31:0] $end
$scope module tba $end
$var wire 2 ( A [1:0] $end
$var wire 2 ) B [1:0] $end
$var wire 1 $ Cin $end
$var wire 1 * w1 $end
$var wire 2 + Sum [1:0] $end
$var wire 1 # Cout $end
$scope module add1 $end
$var wire 1 , A $end
$var wire 1 - B $end
$var wire 1 $ Cin $end
$var wire 1 * Cout $end
$var wire 1 . Sum $end
$var wire 1 / w1 $end
$var wire 1 0 w2 $end
$var wire 1 1 w3 $end
$upscope $end
$scope module add2 $end
$var wire 1 2 A $end
$var wire 1 3 B $end
$var wire 1 * Cin $end
$var wire 1 # Cout $end
$var wire 1 4 Sum $end
$var wire 1 5 w1 $end
$var wire 1 6 w2 $end
$var wire 1 7 w3 $end
$upscope $end
$upscope $end
$upscope $end
$enddefinitions $end
#0
$dumpvars
07
06
05
04
03
02
01
00
0/
0.
0-
0,
b0 +
0*
b0 )
b0 (
b0 '
b0 &
b0 %
0$
0#
b0 "
b0 !
$end
#20
b1 "
b1 +
1.
1-
b1 !
b1 %
b1 )
b1 '
#40
0.
b10 "
b10 +
14
0-
13
b10 !
b10 %
b10 )
b10 '
#60
b11 "
b11 +
1.
1-
b11 !
b11 %
b11 )
b11 '
#80
b1 "
b1 +
04
0-
03
1,
b0 %
b0 )
b1 !
b1 &
b1 (
b100 '
#100
14
1*
b10 "
b10 +
0.
1/
1-
b10 !
b1 %
b1 )
b101 '
#120
0*
0#
1.
0/
b11 "
b11 +
14
07
0-
13
b11 !
b10 %
b10 )
b110 '
#140
1#
04
17
1*
b0 "
b0 +
0.
1/
1-
b100 !
b11 %
b11 )
b111 '
#160
0#
b10 "
b10 +
14
0*
07
0/
06
0-
03
0,
12
b0 %
b0 )
b10 !
b10 &
b10 (
b1000 '
#180
b11 "
b11 +
1.
1-
b11 !
b1 %
b1 )
b1001 '
#200
1#
0.
b0 "
b0 +
04
15
0-
13
b100 !
b10 %
b10 )
b1010 '
#220
b1 "
b1 +
1.
1-
b101 !
b11 %
b11 )
b1011 '
#240
0#
b11 "
b11 +
14
05
0-
03
1,
b0 %
b0 )
b11 !
b11 &
b11 (
b1100 '
#260
1#
04
16
1*
b0 "
b0 +
0.
1/
1-
b100 !
b1 %
b1 )
b1101 '
#280
06
0*
1.
0/
b1 "
b1 +
04
15
07
0-
13
b101 !
b10 %
b10 )
b1110 '
#300
14
16
17
1*
b10 "
b10 +
0.
1/
1-
b110 !
b11 %
b11 )
b1111 '
#320
04
0*
0#
07
0/
05
06
0-
03
0,
02
b1 "
b1 +
1.
00
01
b0 %
b0 )
b0 &
b0 (
b1 !
1$
b10000 '
#340
14
1*
b10 "
b10 +
0.
11
1-
b10 !
b1 %
b1 )
b10001 '
#360
0*
0#
1.
01
b11 "
b11 +
14
07
0-
13
b11 !
b10 %
b10 )
b10010 '
#380
1#
04
17
1*
b0 "
b0 +
0.
11
1-
b100 !
b11 %
b11 )
b10011 '
#400
0#
01
b10 "
b10 +
14
07
10
0-
03
1,
b0 %
b0 )
b10 !
b1 &
b1 (
b10100 '
#420
b11 "
b11 +
1.
1/
11
1-
b11 !
b1 %
b1 )
b10101 '
#440
1#
0.
0/
01
b0 "
b0 +
04
17
0-
13
b100 !
b10 %
b10 )
b10110 '
#460
b1 "
b1 +
1.
1/
11
1-
b101 !
b11 %
b11 )
b10111 '
#480
0#
b11 "
b11 +
14
0*
01
07
0/
00
06
0-
03
0,
12
b0 %
b0 )
b11 !
b10 &
b10 (
b11000 '
#500
1#
04
16
1*
b0 "
b0 +
0.
11
1-
b100 !
b1 %
b1 )
b11001 '
#520
06
0*
1.
01
b1 "
b1 +
04
15
07
0-
13
b101 !
b10 %
b10 )
b11010 '
#540
14
16
17
1*
b10 "
b10 +
0.
11
1-
b110 !
b11 %
b11 )
b11011 '
#560
01
b0 "
b0 +
04
05
07
10
0-
03
1,
b0 %
b0 )
b100 !
b11 &
b11 (
b11100 '
#580
b1 "
b1 +
1.
1/
11
1-
b101 !
b1 %
b1 )
b11101 '
#600
0.
0/
01
b10 "
b10 +
14
15
17
0-
13
b110 !
b10 %
b10 )
b11110 '
#620
b11 "
b11 +
1.
1/
11
1-
b111 !
b11 %
b11 )
b11111 '
#640
04
0*
0#
07
0/
05
06
0-
03
0,
02
b0 "
b0 +
0.
00
01
b0 %
b0 )
b0 &
b0 (
b0 !
0$
b100000 '
